tai_chat/__init__.py
tai_chat/api/.config.json
tai_chat/api/__dev__.py
tai_chat/api/__init__.py
tai_chat/api/__main__.py
tai_chat/api/auth/__init__.py
tai_chat/api/auth/auth_router.py
tai_chat/api/auth/dependencies.py
tai_chat/api/auth/jwt.py
tai_chat/api/config.py
tai_chat/api/database/.diagram.png
tai_chat/api/database/__init__.py
tai_chat/api/database/daos.py
tai_chat/api/database/dtos.py
tai_chat/api/database/models.py
tai_chat/api/database/session_manager.py
tai_chat/api/database/utils.py
tai_chat/api/llm.py
tai_chat/api/resources/__init__.py
tai_chat/api/resources/exceptions.py
tai_chat/api/resources/handlers.py
tai_chat/api/resources/responses.py
tai_chat/api/routers/__init__.py
tai_chat/api/routers/router_chat.py
tai_chat/api/routers/router_chat_activity.py
tai_chat/api/routers/router_enums.py
tai_chat/api/routers/router_mensaje.py
tai_chat/api/routers/router_stream.py
tai_chat/api/routers/router_token_consumption_stats.py
tai_chat/api/routers/router_token_usage.py
tai_chat/api/routers/router_user_stats.py
tai_chat/api/routers/router_usuario.py
tai_chat/api/tools/__init__.py
tai_chat/api/tools/schemas.py
tai_chat/api/tools/toolfuncs.py
tai_chat/api/types.py
tai_chat/api/utils.py
tai_chat/api/websockets.py
tai_chat/cli/commands/__init__.py
tai_chat/cli/commands/cmd_adduser/__init__.py
tai_chat/cli/commands/cmd_adduser/chatbot/crud/syn/__init__.py
tai_chat/cli/commands/cmd_adduser/chatbot/crud/syn/daos.py
tai_chat/cli/commands/cmd_adduser/chatbot/crud/syn/dtos.py
tai_chat/cli/commands/cmd_adduser/chatbot/crud/syn/session_manager.py
tai_chat/cli/commands/cmd_adduser/chatbot/crud/syn/utils.py
tai_chat/cli/commands/cmd_adduser/chatbot/models/__init__.py
tai_chat/cli/commands/cmd_adduser/main.py
tai_chat/cli/commands/cmd_init/__init__.py
tai_chat/cli/commands/cmd_init/main.py
tai_chat/cli/commands/cmd_init/model.py
tai_chat/cli/commands/cmd_pushdb/__init__.py
tai_chat/cli/commands/cmd_pushdb/main.py
tai_chat/cli/main.py
tai_chat/database/.taisqlproject
tai_chat-0.1.7.dist-info/METADATA
tai_chat-0.1.7.dist-info/WHEEL
tai_chat-0.1.7.dist-info/entry_points.txt
tai_chat-0.1.7.dist-info/licenses/LICENSE
tai_chat-0.1.7.dist-info/RECORD
