Metadata-Version: 2.4
Name: tai-chat
Version: 0.1.7
Summary: 
License-File: LICENSE
Author: MateoSaezMata
Author-email: msaez@triplealpha.in
Requires-Python: >=3.10,<4.0
Classifier: Programming Language :: Python :: 3
Classifier: Programming Language :: Python :: 3.10
Classifier: Programming Language :: Python :: 3.11
Classifier: Programming Language :: Python :: 3.12
Classifier: Programming Language :: Python :: 3.13
Classifier: Programming Language :: Python :: 3.14
Requires-Dist: click (>=8.3.0,<9.0.0)
Requires-Dist: tai-sql (>=0.3.39,<0.4.0)
